weatheril/__init__.py
weatheril/consts.py
weatheril/forecast.py
weatheril/radar_satellite.py
weatheril/utils.py
weatheril/warning.py
weatheril/weather.py
weatheril-0.40.2.dist-info/licenses/LICENSE
weatheril-0.40.2.dist-info/METADATA
weatheril-0.40.2.dist-info/WHEEL
weatheril-0.40.2.dist-info/top_level.txt
weatheril-0.40.2.dist-info/RECORD
