Metadata-Version: 2.4
Name: weatheril
Version: 0.40.2
Summary: Israel Meteorological Service unofficial python api wrapper
Home-page: https://github.com/t0mer/py-weatheril
Download-URL: https://pypi.org/project/weatheril/
Author: Tomer Klein
Author-email: tomer.klein@gmail.com
License: MIT
Project-URL: Documentation, https://github.com/t0mer/py-weatheril
Project-URL: Source, https://github.com/t0mer/py-weatheril
Keywords: ims,weatheril,Israel Meteorological Service,Meteorological Service,weather
Classifier: Intended Audience :: Developers
Classifier: Topic :: Software Development :: Build Tools
Classifier: License :: OSI Approved :: MIT License
Classifier: Programming Language :: Python :: 3.6
Classifier: Programming Language :: Python :: 3.7
Classifier: Programming Language :: Python :: 3.8
Classifier: Programming Language :: Python :: 3.9
Classifier: Programming Language :: Python :: 3.10
Classifier: Natural Language :: English
Classifier: Operating System :: OS Independent
Requires-Python: >=3.6
License-File: LICENSE
Requires-Dist: requests
Requires-Dist: pillow
Requires-Dist: pytz
Requires-Dist: urllib3
Requires-Dist: loguru
Dynamic: author
Dynamic: author-email
Dynamic: classifier
Dynamic: description
Dynamic: description-content-type
Dynamic: download-url
Dynamic: home-page
Dynamic: keywords
Dynamic: license
Dynamic: license-file
Dynamic: project-url
Dynamic: requires-dist
Dynamic: requires-python
Dynamic: summary
